ipm/__init__.py
ipm/e2e.py
ipm_e2e-0.0.5.dist-info/LICENSE
ipm_e2e-0.0.5.dist-info/METADATA
ipm_e2e-0.0.5.dist-info/WHEEL
ipm_e2e-0.0.5.dist-info/entry_points.txt
ipm_e2e-0.0.5.dist-info/top_level.txt
ipm_e2e-0.0.5.dist-info/RECORD
