Metadata-Version: 2.1
Name: ipm-e2e
Version: 0.0.5
Summary: "Library used to ease the development of automated tests based on AT-SPI"
Home-page: https://github.com/cabrero/ipm_e2e
Author: David Cabrero Souto
Author-email: "David Cabrero Souto" <david.cabrero@udc.es>
License: GPL-2.0-only
Project-URL: Documentation, https://ipm-e2e.readthedocs.io/en/latest/
Project-URL: Bug Tracker, https://github.com/cabrero/ipm_e2e/issues
Platform: UNKNOWN
Classifier: License :: OSI Approved :: GNU General Public License v2 (GPLv2)
Classifier: Development Status :: 4 - Beta
Classifier: Environment :: Console
Classifier: Intended Audience :: Developers
Classifier: Programming Language :: Python :: 3
Classifier: Topic :: Scientific/Engineering :: Human Machine Interfaces
Classifier: Topic :: Software Development :: Quality Assurance
Classifier: Topic :: Software Development :: Testing
Classifier: Topic :: Software Development :: Testing :: Acceptance
Classifier: Topic :: Software Development :: Testing :: BDD
Classifier: Topic :: Software Development :: User Interfaces
Requires-Python: >=3.9
License-File: LICENSE
